chronologix/__init__.py
chronologix/cleanup.py
chronologix/compression.py
chronologix/config.py
chronologix/errors.py
chronologix/hooks.py
chronologix/io.py
chronologix/manager.py
chronologix/rollover.py
chronologix/state.py
chronologix/utils.py
chronologix-0.10.0.dist-info/licenses/LICENSE
chronologix-0.10.0.dist-info/METADATA
chronologix-0.10.0.dist-info/WHEEL
chronologix-0.10.0.dist-info/top_level.txt
chronologix-0.10.0.dist-info/RECORD
