Metadata-Version: 2.4
Name: chronologix
Version: 0.10.0
Summary: Asynchronous, modular Python logger with time-based rollover, level filtering, multi-sink output, and more.
Author: Fractalwillie
License: MIT License
Project-URL: Homepage, https://github.com/fractalwillie/chronologix
Project-URL: Issues, https://github.com/fractalwillie/chronologix/issues
Classifier: Development Status :: 4 - Beta
Classifier: Intended Audience :: Developers
Classifier: Programming Language :: Python :: 3
Classifier: Programming Language :: Python :: 3.9
Classifier: Programming Language :: Python :: 3.10
Classifier: Programming Language :: Python :: 3.11
Classifier: Programming Language :: Python :: 3.12
Classifier: Programming Language :: Python :: 3.13
Classifier: Operating System :: OS Independent
Classifier: License :: OSI Approved :: MIT License
Requires-Python: >=3.9
License-File: LICENSE
Dynamic: license-file
